setup.cfg
setup.py
cephalopod/__init__.py
cephalopod/file_exploration.py
cephalopod/file_handler.py
cephalopod/interact_test_plot.py
cephalopod/interactive_plotting.py
cephalopod/meta.py
cephalopod/path_handler.py
cephalopod/plotting_module.py
cephalopod.egg-info/PKG-INFO
cephalopod.egg-info/SOURCES.txt
cephalopod.egg-info/dependency_links.txt
cephalopod.egg-info/not-zip-safe
cephalopod.egg-info/requires.txt
cephalopod.egg-info/top_level.txt