Metadata-Version: 1.1
Name: cephalopod
Version: 0.15a0
Summary: package to manage SIMS data remotely
Home-page: https://github.com/copperwire/cephalopod.git
Author: Robert Solli
Author-email: octopus.prey@gmail.com
License: MIT
Download-URL: https://github.com/copperwire/cephalopod/tarball/0.14a0
Platform: UNKNOWN
